fpf/__init__.py
fpf/filters.py
fpf/logger.py
fpf/mixins.py
fpf/sample.py
fpf-0.1.4.dist-info/LICENSE
fpf-0.1.4.dist-info/METADATA
fpf-0.1.4.dist-info/WHEEL
fpf-0.1.4.dist-info/top_level.txt
fpf-0.1.4.dist-info/RECORD
