Metadata-Version: 2.1
Name: fpf
Version: 0.1.4
Summary: Filter Paths in Python the easy way
Home-page: UNKNOWN
Author: Filipe Spencer Lopes
Author-email: filipe@spncr.be
License: UNKNOWN
Project-URL: github, https://github.com/fslds/fpf
Project-URL: docs, https://fps.readthedocs.io/
Project-URL: issue, https://github.com/fslds/fpf/issues
Keywords: path filter file ignorefile gitignore
Platform: UNKNOWN
Classifier: Development Status :: 3 - Alpha
Classifier: Intended Audience :: Developers
Classifier: Topic :: Software Development :: Build Tools
Classifier: License :: OSI Approved :: MIT License
Classifier: Programming Language :: Python :: 3.7
Classifier: Programming Language :: Python :: 3.8
Classifier: Programming Language :: Python :: 3.8
Requires-Python: >=3.6.8, <4
Requires-Dist: pathspec
Provides-Extra: dev
Requires-Dist: check-manifest ; extra == 'dev'
Provides-Extra: test
Requires-Dist: coverage ; extra == 'test'
